amaan_ai20_phone_number_validator/__init__.py
amaan_ai20_phone_number_validator/validator.py
amaan_ai20_phone_number_validator-0.1.1.dist-info/METADATA
amaan_ai20_phone_number_validator-0.1.1.dist-info/WHEEL
amaan_ai20_phone_number_validator-0.1.1.dist-info/RECORD
