Metadata-Version: 2.1
Name: amaan-ai20-phone-number-validator
Version: 0.1.1
Summary: 
Author: amaan-ai20
Author-email: amaan@ai20labs.com
Requires-Python: >=3.12,<4.0
Classifier: Programming Language :: Python :: 3
Classifier: Programming Language :: Python :: 3.12
Classifier: Programming Language :: Python :: 3.13
Requires-Dist: requests (>=2.32.3,<3.0.0)
